py12box/__init__.py
py12box/core.py
py12box/model.py
py12box/startup.py
py12box/util.py
py12box/data/example/CFC-11/CFC-11_emissions.csv
py12box/data/example/CFC-11/CFC-11_initial_conditions.csv
py12box/data/example/CHCl3/CHCl3_emissions.csv
py12box/data/example/CHCl3/CHCl3_initial_conditions.csv
py12box/data/example/HFC-134a/HFC-134a_emissions.csv
py12box/data/example/HFC-134a/HFC-134a_initial_conditions.csv
py12box/data/example/SF6/SF6_emissions.csv
py12box/data/example/SF6/SF6_initial_conditions.csv
py12box/data/inputs/Cl.npy
py12box/data/inputs/OH.npy
py12box/data/inputs/invlifetime_relative_strat.npy
py12box/data/inputs/species_info.csv
py12box/data/inputs/temperature.npy
py12box/data/inputs/transport.npz
py12box-0.2.2.dist-info/LICENSE
py12box-0.2.2.dist-info/METADATA
py12box-0.2.2.dist-info/WHEEL
py12box-0.2.2.dist-info/top_level.txt
py12box-0.2.2.dist-info/RECORD
