Metadata-Version: 2.1
Name: py12box
Version: 0.2.2
Summary: AGAGE 12-box model
Author-email: Matt Rigby <matt.rigby@bristol.ac.uk>
License: MIT License        
Project-URL: Homepage, https://github.com/mrghg/py12box
Project-URL: Bug Tracker, https://github.com/mrghg/py12box/issues
Classifier: Programming Language :: Python :: 3
Classifier: License :: OSI Approved :: MIT License
Classifier: Operating System :: OS Independent
Classifier: Development Status :: 5 - Production/Stable
Classifier: Intended Audience :: Science/Research
Requires-Python: >=3.7
License-File: LICENSE
Requires-Dist: numpy
Requires-Dist: pandas
Requires-Dist: numba (==0.55.*)
Requires-Dist: scipy
